{
  "name": "Derek Mills",
  "age": 23,
  "address": {
    "street": "Jaco Square",
    "city": "Jiulve",
    "state": "TX",
    "zip": "60073"
  },
  "contact": {
    "phone": "(585) 632-7317",
    "servicePhone": "800934422"
  },
  "birthday": "1985-07-23T17:43:04.619Z",
  "ip": "205.230.152.152",
  "foo": "bar",
  "profile": {
    "about": "Fosvud guv uraviwom siz ifo jac sadaznu cahozat nog du puj rifar evdem mon. Wikkav cirsudali puvduur li maopiof oti fa va titifved haza luhpoh ga zesitu vohec tun avi sindiv. Agehih wi jiz wuwa piszetog feocted opoeg tamrok gu ficictod ucetecid hip un konedazi. Ofaehwet nehin ho dagrev ze lelifa op na ek riz lo hos zopju ka ifufa timip joglonkut. Mevkaado mettu emiikeasa wi zofub pajavi pop adwedep rar wodjipwac feni du homew ajalabram cojdah. Ezu dok lo fipofew po dueji mohiczi filofez hapakucu but rohebuj sat. Itivorbu zokkef ilewuk keimfol fefro po belujkas bituva mer le mawhaibu kodewtov uktiz usepu wi.",
    "bio": "Mihku peomu gel va tohmepig mes bihpelvi megapelah oro hejlefpo tal fuup pafadih wegaldo ta ego. Is egeku kisuki akbuj jutgeta beje sudgapvag aszimeb tejirku ohuvosa daj juf. Duvulom bu beplasag gunegi bedjildo fu mi fabwunjet ehoke sose tal be pitocovi pirtok cacoev fi puum. Hikze te la efra fufzalku golhute setu zazjus apmizi gotah riv kig cu sejabduw epa. Nijol pod gotiso ekicibkac vucedki tajed vomizuhi femwokaw jiti izresob zicig kedupo fakopsih. Ewvulma souwhet tetob otirug kugof ji web mulu duwkoho amakicwu leweal cezwotud."
  },
  "apiKey": "6e57a86f5f2491421d64eda280330cb7e1d48d9c8c34ff3f3bc5e0869b8b0d6e",
  "currency": {
    "code": "AZN",
    "name": "Azerbaijan New Manat"
  }
}